num2word_greek/__init__.py
num2word_greek/__main__.py
num2word_greek/convert_numbers.py
num2word_greek/numbers2words.py
num2word_greek/prefixes.py
num2word_greek/py.typed
num2word_greek/utils.py
numbers2words_greek-0.0.2a0.dist-info/entry_points.txt
numbers2words_greek-0.0.2a0.dist-info/LICENSE
numbers2words_greek-0.0.2a0.dist-info/WHEEL
numbers2words_greek-0.0.2a0.dist-info/METADATA
numbers2words_greek-0.0.2a0.dist-info/RECORD
