Metadata-Version: 2.1
Name: numbers2words-greek
Version: 0.0.2a0
Summary: Numbers2Words Greek
Home-page: https://github.com/geoph9/Numbers2Words-Greek
License: MIT
Author: Georgios K.
Author-email: geoph9@protonmail.com
Requires-Python: >=3.7,<4.0
Classifier: Development Status :: 2 - Pre-Alpha
Classifier: License :: OSI Approved :: MIT License
Classifier: Programming Language :: Python :: 3
Classifier: Programming Language :: Python :: 3.10
Classifier: Programming Language :: Python :: 3.7
Classifier: Programming Language :: Python :: 3.8
Classifier: Programming Language :: Python :: 3.9
Requires-Dist: click (>=8.0.1)
Project-URL: Changelog, https://github.com/geoph9/Numbers2Words-Greek/releases
Project-URL: Documentation, https://Numbers2Words-Greek.readthedocs.io
Project-URL: Repository, https://github.com/geoph9/Numbers2Words-Greek
